django_cascading_dropdown_widget/__init__.py
django_cascading_dropdown_widget/widgets.py
django_cascading_dropdown_widget/migrations/__init__.py
django_cascading_dropdown_widget/static/django-cascading-dropdown-widget/css/django-cascading-dropdown-widget.css
django_cascading_dropdown_widget/static/django-cascading-dropdown-widget/js/django-cascading-dropdown-widget.js
django_cascading_dropdown_widget/templates/django-cascading-dropdown-widget/django-cascading-dropdown-widget.html
django_cascading_dropdown_widget-0.2.8.dist-info/licenses/LICENSE
django_cascading_dropdown_widget-0.2.8.dist-info/METADATA
django_cascading_dropdown_widget-0.2.8.dist-info/WHEEL
django_cascading_dropdown_widget-0.2.8.dist-info/top_level.txt
django_cascading_dropdown_widget-0.2.8.dist-info/RECORD
