Metadata-Version: 2.4
Name: django-cascading-dropdown-widget
Version: 0.2.8
Summary: Provide a cascading-dropdown widget for django.
Author: rRR0VrFP
Maintainer: rRR0VrFP
License: MIT
Keywords: django admin extentions,django cascading dropdown widget
Classifier: Development Status :: 5 - Production/Stable
Classifier: Intended Audience :: Developers
Classifier: Topic :: Software Development :: Libraries :: Python Modules
Classifier: License :: OSI Approved :: MIT License
Classifier: Programming Language :: Python :: 3
Classifier: Programming Language :: Python :: 3 :: Only
License-File: LICENSE
Requires-Dist: django
Dynamic: author
Dynamic: classifier
Dynamic: description
Dynamic: description-content-type
Dynamic: keywords
Dynamic: license
Dynamic: license-file
Dynamic: maintainer
Dynamic: requires-dist
Dynamic: summary
